emcnet/__init__.py
emcnet/dashboard.py
emcnet/emcnet_data_processor.py
emcnet/emcnet_data_publisher.py
emcnet/emcnet_data_store.py
emcnet/emcnet_recorder.py
emcnet/server_data_store.py
emcnet/device/Adafruit_DHT_Em.py
emcnet/device/__init__.py
emcnet/device/device_socket.py
emcnet/device/dht22.py
emcnet/device/emcnet_battery_soc.py
emcnet/device/ina226.py
emcnet/device/ina226_fake.py
emcnet/device/ina226_publish.py
emcnet/device/mcp3008_rpi.py
emcnet/device/vedirect_types.py
emcnet/device/vmppt.py
emcnet/device/vmppt_publish.py
emcnet/device/vmppt_store.py
emcnet/webserver/__init__.py
emcnet/webserver/assets.py
emcnet/webserver/config.py
emcnet/webserver/routes.py
emcnet/webserver/wsgi.py
emcnet/webserver/plotlydash/__init__.py
emcnet/webserver/plotlydash/dashboard.py
emcnet/webserver/plotlydash/dashboard_embedded.py
emcnet/webserver/plotlydash/data.py
emcnet/webserver/plotlydash/layout.py
emcnet/webserver/static/img/logo.png
emcnet/webserver/static/less/global.less
emcnet/webserver/static/less/header.less
emcnet/webserver/static/less/home.less
emcnet/webserver/static/less/table.less
emcnet/webserver/templates/analytics.jinja2
emcnet/webserver/templates/index.jinja2
emcnet/webserver/templates/layout.jinja2
emcnet/webserver2/__init__.py
emcnet/webserver2/app1.py
emcnet/webserver2/assets.py
emcnet/webserver2/config.py
emcnet/webserver2/flask_app.py
emcnet/webserver2/newapp.py
emcnet/webserver2/routes.py
emcnet/webserver2/wsgi.py
emcnet/webserver2/plotlydash/__init__.py
emcnet/webserver2/plotlydash/dashboard.py
emcnet/webserver2/plotlydash/dashboard_embedded.py
emcnet/webserver2/plotlydash/data.py
emcnet/webserver2/plotlydash/layout.py
emcnet/webserver2/static/img/logo.png
emcnet/webserver2/static/less/global.less
emcnet/webserver2/static/less/header.less
emcnet/webserver2/static/less/home.less
emcnet/webserver2/static/less/table.less
emcnet/webserver2/templates/analytics.jinja2
emcnet/webserver2/templates/index.jinja2
emcnet/webserver2/templates/layout.jinja2
emcnet-1.4.1.dist-info/LICENSE
emcnet-1.4.1.dist-info/METADATA
emcnet-1.4.1.dist-info/WHEEL
emcnet-1.4.1.dist-info/entry_points.txt
emcnet-1.4.1.dist-info/top_level.txt
emcnet-1.4.1.dist-info/RECORD
