Metadata-Version: 2.1
Name: emcnet
Version: 1.4.1
Summary: Infrastructure for recording and dashboarding distributed device data with intermittent connectivity
Author: J. M. Fife
Author-email: jmfife@gmail.com
Classifier: Programming Language :: Python :: 3
Requires-Python: >=3.8
License-File: LICENSE
Requires-Dist: pandas (>=1.2.3)
Requires-Dist: python-dotenv (>=0.15.0)
Requires-Dist: codetiming (>=1.3.0)
Requires-Dist: influxdb-client[ciso]
Requires-Dist: paho-mqtt
Requires-Dist: python-dotenv
Requires-Dist: fieldday
Requires-Dist: vedirect-jmfife
Requires-Dist: smbus2
Requires-Dist: fifeutil
Provides-Extra: test
Requires-Dist: pytest ; extra == 'test'
